{"user_id": "USR-5C04450C9EC142448D6968643F6B2157", "first_name": "Kari", "last_name": "Smith", "email": "audrey13@example.net", "gender": "Female", "age": 24, "country": "UK", "city": "West Walter", "preferred_language": "English", "preferred_genre": "Drama", "device_type": "Mobile", "profile_type": "Kids", "signup_date": "2026-07-21", "account_status": "Active", "subscription_plan": "Premium"}
{"user_id": "USR-200B308A262141E1ABB59CD35E12581B", "first_name": "Michael", "last_name": "Rice", "email": "qlawrence@example.org", "gender": "Male", "age": 53, "country": "USA", "city": "Campbellville", "preferred_language": "English", "preferred_genre": "Fantasy", "device_type": "Apple TV", "profile_type": "Kids", "signup_date": "2026-07-21", "account_status": "Active", "subscription_plan": "Premium"}
{"user_id": "USR-B9153C48669148D5A3E7685ADBB1B15C", "first_name": "Alexander", "last_name": "Arroyo", "email": "tiffanycastillo@example.org", "gender": "Female", "age": 45, "country": "India", "city": "South Susan", "preferred_language": "Hindi", "preferred_genre": "Documentary", "device_type": "Android TV", "profile_type": "Single", "signup_date": "2026-07-21", "account_status": "Active", "subscription_plan": "Standard"}
{"user_id": "USR-15848524D2304FF2B2F1CFCC0894F369", "first_name": "Isabella", "last_name": "Oconnor", "email": "danielsharp@example.net", "gender": "Female", "age": 53, "country": "Australia", "city": "Robertomouth", "preferred_language": "English", "preferred_genre": "Horror", "device_type": "Android TV", "profile_type": "Family", "signup_date": "2026-07-21", "account_status": "Active", "subscription_plan": "Standard"}
{"user_id": "USR-824459B2C76647B694293CE17A60227B", "first_name": "Ashley", "last_name": "Joyce", "email": "jason06@example.net", "gender": "Male", "age": 74, "country": "USA", "city": "West Jenniferstad", "preferred_language": "English", "preferred_genre": "Thriller", "device_type": "Apple TV", "profile_type": "Family", "signup_date": "2026-07-21", "account_status": "Active", "subscription_plan": "Premium"}
