{"user_id": "USR-BC80BAA38E3243379F91CF0D3644BF3F", "first_name": "Lori", "last_name": "Myers", "email": "william73@example.com", "gender": "Male", "age": 36, "country": "India", "city": "New Mariemouth", "preferred_language": "Hindi", "preferred_genre": "Fantasy", "device_type": "Fire TV", "profile_type": "Family", "signup_date": "2026-07-23", "account_status": "Active", "subscription_plan": "Premium"}
{"user_id": "USR-1FF323A2DFEB40509E9A0103F24DE78E", "first_name": "Jasmine", "last_name": "Cox", "email": "sgonzalez@example.net", "gender": "Male", "age": 21, "country": "India", "city": "South Sarah", "preferred_language": "Hindi", "preferred_genre": "Thriller", "device_type": "Mobile", "profile_type": "Family", "signup_date": "2026-07-23", "account_status": "Active", "subscription_plan": "Premium"}
{"user_id": "USR-5B9D36542D6047DBB1A18AC855A52300", "first_name": "Paige", "last_name": "Martin", "email": "danielwilson@example.net", "gender": "Male", "age": 37, "country": "USA", "city": "Moorefort", "preferred_language": "English", "preferred_genre": "Action", "device_type": "Apple TV", "profile_type": "Family", "signup_date": "2026-07-23", "account_status": "Active", "subscription_plan": "Standard"}
{"user_id": "USR-12A0E69D9D0E421C8CBD0E0B23340F7A", "first_name": "Jacob", "last_name": "Gray", "email": "tmoore@example.net", "gender": "Female", "age": 27, "country": "India", "city": "Vincentland", "preferred_language": "Hindi", "preferred_genre": "Horror", "device_type": "Smart TV", "profile_type": "Kids", "signup_date": "2026-07-23", "account_status": "Active", "subscription_plan": "Standard"}
{"user_id": "USR-931A7FFF2DC74507BB9F66127CC069C4", "first_name": "Nicolas", "last_name": "Ball", "email": "vmorgan@example.com", "gender": "Male", "age": 36, "country": "Canada", "city": "Bradleyville", "preferred_language": "English", "preferred_genre": "Sci-Fi", "device_type": "Laptop", "profile_type": "Family", "signup_date": "2026-07-23", "account_status": "Active", "subscription_plan": "Standard"}
{"user_id": "USR-DE7D665EFC334358B0B6157C22CF94AA", "first_name": "Tracie", "last_name": "Harris", "email": "hallamber@example.net", "gender": "Male", "age": 52, "country": "USA", "city": "Clarkview", "preferred_language": "English", "preferred_genre": "Drama", "device_type": "Tablet", "profile_type": "Family", "signup_date": "2026-07-23", "account_status": "Active", "subscription_plan": "Basic"}
{"user_id": "USR-6834CEF2DB2240E7990BA3456816BDAF", "first_name": "Karl", "last_name": "Moody", "email": "rodriguezamy@example.com", "gender": "Female", "age": 53, "country": "USA", "city": "West Amanda", "preferred_language": "English", "preferred_genre": "Documentary", "device_type": "Smart TV", "profile_type": "Family", "signup_date": "2026-07-23", "account_status": "Active", "subscription_plan": "Standard"}
{"user_id": "USR-010BC2A8BE4946F987A593F13707CA2C", "first_name": "Victoria", "last_name": "Austin", "email": "tpeterson@example.net", "gender": "Female", "age": 75, "country": "UK", "city": "New Masonfort", "preferred_language": "English", "preferred_genre": "Documentary", "device_type": "Tablet", "profile_type": "Single", "signup_date": "2026-07-23", "account_status": "Active", "subscription_plan": "Standard"}
{"user_id": "USR-A758E9ABD6674877AED54553DCB19311", "first_name": "Luke", "last_name": "Barnes", "email": "hernandezjessica@example.com", "gender": "Male", "age": 64, "country": "UK", "city": "Stacyberg", "preferred_language": "English", "preferred_genre": "Action", "device_type": "Fire TV", "profile_type": "Single", "signup_date": "2026-07-23", "account_status": "Active", "subscription_plan": "Standard"}
