{"user_id": "USR-6F36793B05F448D8B2F3C9186DD4AA5D", "first_name": "Zachary", "last_name": "Cuevas", "email": "abbottchristian@example.net", "gender": "Female", "age": 48, "country": "Australia", "city": "Leetown", "preferred_language": "English", "preferred_genre": "Crime", "device_type": "Fire TV", "profile_type": "Family", "signup_date": "2026-07-23", "account_status": "Active", "subscription_plan": "Premium"}
{"user_id": "USR-41AC668B6A4241CD807B537ED063A6D4", "first_name": "Ryan", "last_name": "Ward", "email": "tjones@example.net", "gender": "Female", "age": 67, "country": "UK", "city": "West George", "preferred_language": "English", "preferred_genre": "Horror", "device_type": "Tablet", "profile_type": "Kids", "signup_date": "2026-07-23", "account_status": "Active", "subscription_plan": "Standard"}
{"user_id": "USR-9B2374DB3F584A249393A198A28F0C65", "first_name": "Linda", "last_name": "Rodriguez", "email": "heathershaw@example.org", "gender": "Female", "age": 58, "country": "UK", "city": "East Carlosbury", "preferred_language": "English", "preferred_genre": "Documentary", "device_type": "Smart TV", "profile_type": "Kids", "signup_date": "2026-07-23", "account_status": "Active", "subscription_plan": "Premium"}
{"user_id": "USR-9F05013D8A1E4F969EEDF1BFDA7B6E3E", "first_name": "Brian", "last_name": "Stone", "email": "rojaselizabeth@example.org", "gender": "Male", "age": 63, "country": "India", "city": "West Monicafurt", "preferred_language": "Hindi", "preferred_genre": "Romance", "device_type": "Smart TV", "profile_type": "Kids", "signup_date": "2026-07-23", "account_status": "Active", "subscription_plan": "Standard"}
{"user_id": "USR-4167B600114C406EBA6E09BB924B98A1", "first_name": "Christopher", "last_name": "Cole", "email": "katie25@example.org", "gender": "Female", "age": 46, "country": "UK", "city": "South Douglas", "preferred_language": "English", "preferred_genre": "Drama", "device_type": "Laptop", "profile_type": "Family", "signup_date": "2026-07-23", "account_status": "Active", "subscription_plan": "Standard"}
{"user_id": "USR-84C2650C657F45E3984DBDF3DE556338", "first_name": "Sherry", "last_name": "Foster", "email": "rachelcox@example.net", "gender": "Female", "age": 73, "country": "UK", "city": "Christophermouth", "preferred_language": "English", "preferred_genre": "Action", "device_type": "Mobile", "profile_type": "Family", "signup_date": "2026-07-23", "account_status": "Active", "subscription_plan": "Basic"}
{"user_id": "USR-C517FBAF883349159D7967157E265968", "first_name": "Susan", "last_name": "Mendez", "email": "lynn51@example.org", "gender": "Male", "age": 40, "country": "India", "city": "Brianfort", "preferred_language": "Hindi", "preferred_genre": "Sci-Fi", "device_type": "Android TV", "profile_type": "Family", "signup_date": "2026-07-23", "account_status": "Active", "subscription_plan": "Basic"}
{"user_id": "USR-6DA1D1674D87434CA84F2E664B005DA3", "first_name": "Joshua", "last_name": "Morris", "email": "haley62@example.net", "gender": "Male", "age": 55, "country": "UK", "city": "Silvastad", "preferred_language": "English", "preferred_genre": "Thriller", "device_type": "Fire TV", "profile_type": "Single", "signup_date": "2026-07-23", "account_status": "Active", "subscription_plan": "Premium"}
{"user_id": "USR-99B7E75291DE475B85F34CBA6FB22A4B", "first_name": "Kayla", "last_name": "Massey", "email": "adamwillis@example.org", "gender": "Female", "age": 63, "country": "India", "city": "West Leroy", "preferred_language": "Hindi", "preferred_genre": "Drama", "device_type": "Tablet", "profile_type": "Kids", "signup_date": "2026-07-23", "account_status": "Active", "subscription_plan": "Basic"}
